Metadata-Version: 1.0
Name: gaubi-dists
Version: 1.0
Summary: Gaussian & Binomial distributions
Home-page: UNKNOWN
Author: Bernardo Garcia
Author-email: bergr7@gmail.com
License: UNKNOWN
Platform: UNKNOWN
